[
    {"cname": "Programming Concepts", "category": "Programming"},
    {"cname": "General Chemistry I", "category": "Chemistry"},
    {"cname": "Experimental General Chemistry I", "category": "Chemistry"},
    {"cname": "Calaculus I", "category": "Math"},
    {"cname": "Fundamentals of Database", "category": "Database"},
    {"cname": "OOP", "category":"Programming"},
    {"cname": "Cybersecurity", "category":"Security"},
    {"cname": "Fundamentals of Web Development", "category":"Programming"}
  ]
  